{"id":"com.sina.emotions2015-06","version":13,"display_only":1,"emoticons":[{"chs":"[\u9759\u9999\u5fae\u7b11]","cht":"[\u9759\u9999\u5fae\u7b11]","en":"[]","png":"jiqimaojingxiang_mobile.png","type":0},{"chs":"[\u5927\u96c4\u5fae\u7b11]","cht":"[\u5927\u96c4\u5fae\u7b11]","en":"[]","png":"jiqimaodaxiong_mobile.png","type":0},{"chs":"[\u80d6\u864e\u5fae\u7b11]","cht":"[\u80d6\u864e\u5fae\u7b11]","en":"[]","png":"jiqimaopanghu_mobile.png","type":0},{"chs":"[\u5c0f\u592b\u5fae\u7b11]","cht":"[\u5c0f\u592b\u5fae\u7b11]","en":"[]","png":"jiqimaoxiaofu_mobile.png","type":0},{"chs":"[\u751c\u99a8\u4e0d\u60f3\u957f\u5927]","cht":"[\u751c\u99a8\u4e0d\u60f3\u957f\u5927]","en":"[]","png":"bbhltianxinbuxiangzhangda_mobile.png","type":0},{"chs":"[\u6c42\u62b1\u62b1]","cht":"[\u6c42\u62b1\u62b1]","en":"[]","png":"bbhlqiubaobao_mobile.png","type":0},{"chs":"[\u54c6\u5566A\u68a6\u6c57]","cht":"[\u54c6\u5566A\u5922\u6c57]","en":"[]","png":"dorahan_mobile.png","type":0},{"chs":"[\u54c6\u5566A\u68a6\u82b1\u5fc3]","cht":"[\u54c6\u5566A\u5922\u82b1\u5fc3]","en":"[]","png":"dorahaose_mobile.png","type":0},{"chs":"[\u54c6\u5566A\u68a6\u5403\u60ca]","cht":"[\u54c6\u5566A\u5922\u5403\u9a5a]","en":"[]","png":"dorachijing_mobile.png","type":0},{"chs":"[\u54c6\u5566A\u68a6\u5bb3\u6015]","cht":"[\u54c6\u5566A\u5922\u5bb3\u6015]","en":"[]","png":"dorahaipa_mobile.png","type":0},{"chs":"[\u770b\u8dcc]","cht":"[\u770b\u8dcc]","en":"[]","png":"kandiev2_mobile.png","type":0},{"chs":"[\u770b\u6da8]","cht":"[\u770b\u6f32]","en":"[]","png":"kanzhangv2_mobile.png","type":0},{"chs":"[\u7236\u4eb2\u8282]","cht":"[\u7236\u89aa\u7bc0]","en":"[]","png":"fuqinjie2015_mobile.png","type":0},{"chs":"[\u751c\u99a8\u54ed\u54ed]","cht":"[\u751c\u99a8\u54ed\u54ed]","en":"[]","png":"bbhltianxinkk_mobile.png","type":0},{"chs":"[\u5c0a\u4e0a\u4e48\u4e48\u54d2]","cht":"[\u5c0a\u4e0a\u4e48\u4e48\u54d2]","en":"[]","png":"hqgzunshangv1_mobile.png","type":0},{"chs":"[\u751c\u99a8\u7231\u4f60\u54df]","cht":"[\u751c\u99a8\u7231\u4f60\u54df]","en":"[]","png":"bbhltianxinlove_mobile.png","type":0}]}